{
  "restaurant": {
    "id": "aaa59df9-d68a-40ff-8b6e-5aea2a594d9c",
    "name": "Dirty Martin's Place",
    "price": "$"
  },
  "analysis": {
    "timestamp": "2025-12-05T23:01:14.063Z",
    "scores": {
      "flavorful": 7,
      "authentic": 6,
      "satisfying": 8,
      "comforting": 9,
      "aromatic": 6,
      "appetizing": 7,
      "overall": 7
    },
    "imageTags": [
      "classic roadside eatery",
      "historic Americana vibe",
      "vintage neon lighting",
      "retro diner exterior",
      "evening casual setting",
      "checkered paper liner",
      "fresh lettuce topping",
      "pickles inside burger",
      "crispy sweet potato fries",
      "sesame seed bun",
      "thinly sliced pickles",
      "checkerboard paper lining",
      "classic hamburger bun",
      "juicy beef patty",
      "sesame seed topping",
      "vintage building facade",
      "historic burger joint",
      "iconic restaurant signage",
      "outdoor evening view",
      "rustic western theme",
      "community bench seating",
      "large flat screen TVs",
      "vintage wall decor",
      "casual sports bar",
      "brightly lit interior",
      "outdoor casual seating",
      "retro diner facade",
      "simple wooden architecture",
      "nostalgic roadside attraction",
      "vintage Coca-Cola signage",
      "sauce",
      "burger",
      "lettuce",
      "tots",
      "crisp",
      "juicy cheeseburger deluxe",
      "buttery toasted bun",
      "crispy onion rings",
      "greasy diner indulgence",
      "classic burger toppings"
    ],
    "reviewTags": [
      "bacon-enhanced o.t. special",
      "classic austrian hangout",
      "juicy angus beef patties",
      "student-friendly atmosphere",
      "signature kumbak cheeseburger",
      "large kumback burger",
      "val's grilled chicken sandwich",
      "root beer floats",
      "nostalgic restaurant",
      "corner room with screens",
      "big red shake",
      "bacon cheeseburger",
      "fried pickles",
      "friendly staff",
      "quick service",
      "chili cheese burger",
      "phenomenal burger",
      "very welcoming",
      "delicious food",
      "amazing staff",
      "looking at all the photos",
      "fried pickles are the bomb",
      "hamburgers to die for",
      "best milkshakes ever",
      "retro nostalgic vibe"
    ]
  }
}