{
  "restaurant": {
    "id": "9505d12f-87db-43ee-9a19-176c3b80ea59",
    "name": "Tsuke Edomae",
    "price": "$$"
  },
  "analysis": {
    "timestamp": "2025-12-05T21:46:02.529Z",
    "scores": {
      "vibrant": 4,
      "romantic": 8,
      "trendy": 6,
      "stylish": 8,
      "immersive": 7,
      "inviting": 8,
      "overall": 7
    },
    "imageTags": [
      "elegant dining setup",
      "wooden serving box",
      "garnished with leaves",
      "delicate sashimi presentation",
      "fresh fish slices",
      "caramelized crust dessert",
      "minimalist dessert plate",
      "simple presentation style",
      "creamy custard filling",
      "crispy glazed topping",
      "fresh tuna sushi",
      "expertly sliced fish",
      "traditional Japanese delicacy",
      "minimalist wooden platter",
      "artfully presented sushi",
      "elegant dining setup",
      "traditional wood furnishings",
      "artistic wall projection",
      "intimate sushi counter",
      "minimalist Japanese decor",
      "authentic Japanese cuisine",
      "delicate fish texture",
      "artisan sushi presentation",
      "minimalist marble plate",
      "fresh tuna sashimi",
      "fine ceramic plate",
      "freshly prepared nigiri",
      "handcrafted seafood delicacy",
      "delicate shrimp sushi",
      "minimalist sushi presentation",
      "gold and white design",
      "intricate patterned plate",
      "delicate rice portion",
      "elegant sushi presentation",
      "fresh sea urchin sushi",
      "garnished with scallions",
      "fresh sashimi presentation",
      "elaborate ceramic platter",
      "traditional Japanese dishware",
      "vibrant artistic design"
    ],
    "reviewTags": [
      "perfectly balanced sushi",
      "surprising uni highlight",
      "exceptional fish quality",
      "minimalist small space",
      "intimate and fun experience",
      "inviting cozy environment",
      "richness and saltiness balance",
      "perfectly marinated tuna",
      "best sushi in austin",
      "chef's attention to detail",
      "high-quality sashimi",
      "excellent uni selection",
      "fresh sushi",
      "delicate seasoning",
      "personable chef",
      "chit chat atmosphere",
      "best quality sushi",
      "passion for sushi",
      "small setting",
      "intimate experience",
      "amazing birthday dinner",
      "chef mike stories",
      "omakase experience",
      "make reservations",
      "taken care of"
    ]
  }
}